carreralib/__init__.py
carreralib/__main__.py
carreralib/ble.py
carreralib/connection.py
carreralib/cu.py
carreralib/fw.py
carreralib/protocol.py
carreralib/serial.py
carreralib-1.0.3.dist-info/LICENSE
carreralib-1.0.3.dist-info/METADATA
carreralib-1.0.3.dist-info/WHEEL
carreralib-1.0.3.dist-info/top_level.txt
carreralib-1.0.3.dist-info/RECORD
