Metadata-Version: 2.2
Name: carreralib
Version: 1.0.3
Summary: Python interface to Carrera(R) DIGITAL 124/132 slotcar systems
Home-page: https://github.com/tkem/carreralib/
Author: Thomas Kemmer
Author-email: tkemmer@computer.org
License: MIT
Classifier: Development Status :: 5 - Production/Stable
Classifier: Environment :: Other Environment
Classifier: Intended Audience :: Developers
Classifier: License :: OSI Approved :: MIT License
Classifier: Operating System :: MacOS :: MacOS X
Classifier: Operating System :: Microsoft :: Windows :: Windows 10
Classifier: Operating System :: POSIX :: Linux
Classifier: Programming Language :: Python
Classifier: Programming Language :: Python :: 3
Classifier: Programming Language :: Python :: 3.7
Classifier: Programming Language :: Python :: 3.8
Classifier: Programming Language :: Python :: 3.9
Classifier: Programming Language :: Python :: 3.10
Classifier: Programming Language :: Python :: 3.11
Classifier: Programming Language :: Python :: 3.12
Classifier: Programming Language :: Python :: 3.13
Classifier: Topic :: Software Development :: Libraries :: Python Modules
Requires-Python: >=3.7
License-File: LICENSE
Requires-Dist: bleak>=0.19.5
Requires-Dist: pyserial>=3.5
Requires-Dist: windows-curses; platform_system == "Windows"
